{
  "version": "5",
  "dialect": "mysql",
  "id": "0a57e959-307d-4b9f-870b-2108db1188b0",
  "prevId": "00000000-0000-0000-0000-000000000000",
  "tables": {
    "email_list": {
      "name": "email_list",
      "columns": {
        "email": {
          "name": "email",
          "type": "varchar(255)",
          "primaryKey": false,
          "notNull": true,
          "autoincrement": false
        },
        "subscribed_at": {
          "name": "subscribed_at",
          "type": "datetime",
          "primaryKey": false,
          "notNull": true,
          "autoincrement": false
        },
        "unsubscribed_at": {
          "name": "unsubscribed_at",
          "type": "datetime",
          "primaryKey": false,
          "notNull": false,
          "autoincrement": false
        },
        "key": {
          "name": "key",
          "type": "varchar(20)",
          "primaryKey": false,
          "notNull": true,
          "autoincrement": false
        }
      },
      "indexes": {},
      "foreignKeys": {},
      "compositePrimaryKeys": {
        "email_list_email": {
          "name": "email_list_email",
          "columns": [
            "email"
          ]
        }
      },
      "uniqueConstraints": {}
    },
    "order": {
      "name": "order",
      "columns": {
        "stripe_order_id": {
          "name": "stripe_order_id",
          "type": "varchar(100)",
          "primaryKey": false,
          "notNull": true,
          "autoincrement": false
        },
        "stripe_customer_id": {
          "name": "stripe_customer_id",
          "type": "varchar(100)",
          "primaryKey": false,
          "notNull": false,
          "autoincrement": false
        },
        "total_price": {
          "name": "total_price",
          "type": "int",
          "primaryKey": false,
          "notNull": true,
          "autoincrement": false
        },
        "timestamp": {
          "name": "timestamp",
          "type": "timestamp",
          "primaryKey": false,
          "notNull": true,
          "autoincrement": false
        },
        "status": {
          "name": "status",
          "type": "enum('new','placed','packaged','sent')",
          "primaryKey": false,
          "notNull": true,
          "autoincrement": false,
          "default": "'new'"
        }
      },
      "indexes": {},
      "foreignKeys": {},
      "compositePrimaryKeys": {
        "order_stripe_order_id": {
          "name": "order_stripe_order_id",
          "columns": [
            "stripe_order_id"
          ]
        }
      },
      "uniqueConstraints": {}
    },
    "order_product": {
      "name": "order_product",
      "columns": {
        "id": {
          "name": "id",
          "type": "varchar(20)",
          "primaryKey": false,
          "notNull": true,
          "autoincrement": false
        },
        "product_size_code": {
          "name": "product_size_code",
          "type": "varchar(100)",
          "primaryKey": false,
          "notNull": true,
          "autoincrement": false
        },
        "quantity": {
          "name": "quantity",
          "type": "int",
          "primaryKey": false,
          "notNull": true,
          "autoincrement": false
        },
        "order_id": {
          "name": "order_id",
          "type": "varchar(100)",
          "primaryKey": false,
          "notNull": true,
          "autoincrement": false
        }
      },
      "indexes": {},
      "foreignKeys": {},
      "compositePrimaryKeys": {
        "order_product_id": {
          "name": "order_product_id",
          "columns": [
            "id"
          ]
        }
      },
      "uniqueConstraints": {}
    },
    "product": {
      "name": "product",
      "columns": {
        "id": {
          "name": "id",
          "type": "varchar(100)",
          "primaryKey": false,
          "notNull": true,
          "autoincrement": false
        },
        "name": {
          "name": "name",
          "type": "varchar(100)",
          "primaryKey": false,
          "notNull": true,
          "autoincrement": false
        },
        "desc": {
          "name": "desc",
          "type": "text",
          "primaryKey": false,
          "notNull": true,
          "autoincrement": false
        },
        "gradient_color_start": {
          "name": "gradient_color_start",
          "type": "varchar(20)",
          "primaryKey": false,
          "notNull": true,
          "autoincrement": false,
          "default": "'from-red-600'"
        },
        "gradient_color_via": {
          "name": "gradient_color_via",
          "type": "varchar(20)",
          "primaryKey": false,
          "notNull": true,
          "autoincrement": false,
          "default": "'via-purple-500'"
        },
        "gradient_color_end": {
          "name": "gradient_color_end",
          "type": "varchar(20)",
          "primaryKey": false,
          "notNull": true,
          "autoincrement": false,
          "default": "'to-indigo-400'"
        }
      },
      "indexes": {},
      "foreignKeys": {},
      "compositePrimaryKeys": {
        "product_id": {
          "name": "product_id",
          "columns": [
            "id"
          ]
        }
      },
      "uniqueConstraints": {}
    },
    "product_image": {
      "name": "product_image",
      "columns": {
        "cloudinary_id": {
          "name": "cloudinary_id",
          "type": "varchar(255)",
          "primaryKey": false,
          "notNull": true,
          "autoincrement": false
        },
        "product_id": {
          "name": "product_id",
          "type": "varchar(100)",
          "primaryKey": false,
          "notNull": true,
          "autoincrement": false
        },
        "width": {
          "name": "width",
          "type": "int",
          "primaryKey": false,
          "notNull": true,
          "autoincrement": false
        },
        "height": {
          "name": "height",
          "type": "int",
          "primaryKey": false,
          "notNull": true,
          "autoincrement": false
        },
        "is_vertical": {
          "name": "is_vertical",
          "type": "boolean",
          "primaryKey": false,
          "notNull": true,
          "autoincrement": false,
          "default": false
        },
        "order": {
          "name": "order",
          "type": "int",
          "primaryKey": false,
          "notNull": true,
          "autoincrement": false,
          "default": 0
        },
        "is_primary": {
          "name": "is_primary",
          "type": "boolean",
          "primaryKey": false,
          "notNull": true,
          "autoincrement": false,
          "default": false
        }
      },
      "indexes": {},
      "foreignKeys": {},
      "compositePrimaryKeys": {
        "product_image_cloudinary_id": {
          "name": "product_image_cloudinary_id",
          "columns": [
            "cloudinary_id"
          ]
        }
      },
      "uniqueConstraints": {}
    },
    "product_review": {
      "name": "product_review",
      "columns": {
        "id": {
          "name": "id",
          "type": "varchar(100)",
          "primaryKey": false,
          "notNull": true,
          "autoincrement": false
        },
        "rating": {
          "name": "rating",
          "type": "int",
          "primaryKey": false,
          "notNull": true,
          "autoincrement": false
        },
        "review_text": {
          "name": "review_text",
          "type": "text",
          "primaryKey": false,
          "notNull": false,
          "autoincrement": false
        },
        "product_id": {
          "name": "product_id",
          "type": "varchar(100)",
          "primaryKey": false,
          "notNull": false,
          "autoincrement": false
        },
        "timestamp": {
          "name": "timestamp",
          "type": "timestamp",
          "primaryKey": false,
          "notNull": false,
          "autoincrement": false
        }
      },
      "indexes": {},
      "foreignKeys": {},
      "compositePrimaryKeys": {
        "product_review_id": {
          "name": "product_review_id",
          "columns": [
            "id"
          ]
        }
      },
      "uniqueConstraints": {}
    },
    "product_size": {
      "name": "product_size",
      "columns": {
        "code": {
          "name": "code",
          "type": "varchar(100)",
          "primaryKey": false,
          "notNull": true,
          "autoincrement": false
        },
        "name": {
          "name": "name",
          "type": "varchar(255)",
          "primaryKey": false,
          "notNull": true,
          "autoincrement": false,
          "default": "'my product'"
        },
        "is_available": {
          "name": "is_available",
          "type": "boolean",
          "primaryKey": false,
          "notNull": true,
          "autoincrement": false,
          "default": true
        },
        "width": {
          "name": "width",
          "type": "int",
          "primaryKey": false,
          "notNull": true,
          "autoincrement": false
        },
        "height": {
          "name": "height",
          "type": "int",
          "primaryKey": false,
          "notNull": true,
          "autoincrement": false
        },
        "price": {
          "name": "price",
          "type": "int",
          "primaryKey": false,
          "notNull": true,
          "autoincrement": false
        },
        "stripe_price_id": {
          "name": "stripe_price_id",
          "type": "varchar(100)",
          "primaryKey": false,
          "notNull": true,
          "autoincrement": false
        },
        "stripe_product_id": {
          "name": "stripe_product_id",
          "type": "varchar(100)",
          "primaryKey": false,
          "notNull": true,
          "autoincrement": false
        },
        "product_id": {
          "name": "product_id",
          "type": "varchar(100)",
          "primaryKey": false,
          "notNull": true,
          "autoincrement": false
        }
      },
      "indexes": {},
      "foreignKeys": {},
      "compositePrimaryKeys": {
        "product_size_code": {
          "name": "product_size_code",
          "columns": [
            "code"
          ]
        }
      },
      "uniqueConstraints": {}
    },
    "product_tag": {
      "name": "product_tag",
      "columns": {
        "name": {
          "name": "name",
          "type": "varchar(100)",
          "primaryKey": false,
          "notNull": true,
          "autoincrement": false
        },
        "desc": {
          "name": "desc",
          "type": "text",
          "primaryKey": false,
          "notNull": true,
          "autoincrement": false
        }
      },
      "indexes": {},
      "foreignKeys": {},
      "compositePrimaryKeys": {
        "product_tag_name": {
          "name": "product_tag_name",
          "columns": [
            "name"
          ]
        }
      },
      "uniqueConstraints": {}
    },
    "product_to_product_tag": {
      "name": "product_to_product_tag",
      "columns": {
        "product_id": {
          "name": "product_id",
          "type": "varchar(100)",
          "primaryKey": false,
          "notNull": true,
          "autoincrement": false
        },
        "tag_id": {
          "name": "tag_id",
          "type": "varchar(100)",
          "primaryKey": false,
          "notNull": true,
          "autoincrement": false
        }
      },
      "indexes": {},
      "foreignKeys": {},
      "compositePrimaryKeys": {
        "product_to_product_tag_product_id_tag_id_pk": {
          "name": "product_to_product_tag_product_id_tag_id_pk",
          "columns": [
            "product_id",
            "tag_id"
          ]
        }
      },
      "uniqueConstraints": {}
    },
    "session": {
      "name": "session",
      "columns": {
        "id": {
          "name": "id",
          "type": "varchar(100)",
          "primaryKey": false,
          "notNull": true,
          "autoincrement": false
        },
        "user_id": {
          "name": "user_id",
          "type": "varchar(100)",
          "primaryKey": false,
          "notNull": true,
          "autoincrement": false
        },
        "expires_at": {
          "name": "expires_at",
          "type": "timestamp",
          "primaryKey": false,
          "notNull": true,
          "autoincrement": false
        }
      },
      "indexes": {},
      "foreignKeys": {},
      "compositePrimaryKeys": {
        "session_id": {
          "name": "session_id",
          "columns": [
            "id"
          ]
        }
      },
      "uniqueConstraints": {}
    },
    "user": {
      "name": "user",
      "columns": {
        "id": {
          "name": "id",
          "type": "varchar(100)",
          "primaryKey": false,
          "notNull": true,
          "autoincrement": false
        },
        "provider": {
          "name": "provider",
          "type": "enum('google','github')",
          "primaryKey": false,
          "notNull": true,
          "autoincrement": false
        },
        "provider_id": {
          "name": "provider_id",
          "type": "varchar(255)",
          "primaryKey": false,
          "notNull": true,
          "autoincrement": false
        },
        "first_name": {
          "name": "first_name",
          "type": "varchar(100)",
          "primaryKey": false,
          "notNull": true,
          "autoincrement": false
        },
        "last_name": {
          "name": "last_name",
          "type": "varchar(100)",
          "primaryKey": false,
          "notNull": true,
          "autoincrement": false
        },
        "is_admin": {
          "name": "is_admin",
          "type": "boolean",
          "primaryKey": false,
          "notNull": true,
          "autoincrement": false
        },
        "email": {
          "name": "email",
          "type": "varchar(100)",
          "primaryKey": false,
          "notNull": true,
          "autoincrement": false
        },
        "stripe_customer_id": {
          "name": "stripe_customer_id",
          "type": "varchar(100)",
          "primaryKey": false,
          "notNull": false,
          "autoincrement": false
        }
      },
      "indexes": {},
      "foreignKeys": {},
      "compositePrimaryKeys": {
        "user_provider_provider_id_pk": {
          "name": "user_provider_provider_id_pk",
          "columns": [
            "provider",
            "provider_id"
          ]
        }
      },
      "uniqueConstraints": {
        "user_id_unique": {
          "name": "user_id_unique",
          "columns": [
            "id"
          ]
        },
        "user_email_unique": {
          "name": "user_email_unique",
          "columns": [
            "email"
          ]
        },
        "user_stripe_customer_id_unique": {
          "name": "user_stripe_customer_id_unique",
          "columns": [
            "stripe_customer_id"
          ]
        }
      }
    }
  },
  "schemas": {},
  "_meta": {
    "schemas": {},
    "tables": {},
    "columns": {}
  }
}